concordia/Concordia_logic.py
concordia/__init__.py
concordia/_version.py
concordia/create_and_load.py
concordia-0.1.1.dist-info/DESCRIPTION.rst
concordia-0.1.1.dist-info/METADATA
concordia-0.1.1.dist-info/RECORD
concordia-0.1.1.dist-info/WHEEL
concordia-0.1.1.dist-info/metadata.json
concordia-0.1.1.dist-info/top_level.txt
