Metadata-Version: 2.0
Name: concordia
Version: 0.1.1
Summary: Automated monitoring of machine learning models in production. Tracks and finds discrepancies in features, predictions, and labels
Home-page: https://github.com/ClimbsRocks/Concordia
Author: Preston Parry
Author-email: ClimbsBytes@gmail.com
License: MIT
Keywords: machine learning,data science,automated machine learning,deploying,machine learning in production,productionizing machine learning,tracking,feature discrepancies,train/serve skew,train serve skew,train-serve skew,model accuracy,alerts,monitoring,production ready,test coverage
Platform: UNKNOWN
Classifier: Development Status :: 3 - Alpha
Classifier: Intended Audience :: Developers
Classifier: Intended Audience :: Information Technology
Classifier: Intended Audience :: Science/Research
Classifier: Topic :: Scientific/Engineering :: Artificial Intelligence
Classifier: Topic :: Scientific/Engineering :: Information Analysis
Classifier: Topic :: Software Development :: Libraries :: Python Modules
Classifier: License :: OSI Approved :: MIT License
Classifier: Programming Language :: Python :: 2
Classifier: Programming Language :: Python :: 2.7
Classifier: Programming Language :: Python :: 3
Classifier: Programming Language :: Python :: 3.4
Classifier: Programming Language :: Python :: 3.5
Classifier: Programming Language :: Python :: 3.6
Requires-Dist: auto-ml (>=2.9.4)
Requires-Dist: dill (>=0.2.3,<0.3)
Requires-Dist: pymongo (>3.0,<4.0)
Requires-Dist: redis (<3.0,>2.0)
